backtrader_moexalgo/__init__.py
backtrader_moexalgo/moexalgo_feed.py
backtrader_moexalgo/moexalgo_store.py
backtrader_moexalgo-1.0.9.dist-info/LICENSE
backtrader_moexalgo-1.0.9.dist-info/METADATA
backtrader_moexalgo-1.0.9.dist-info/WHEEL
backtrader_moexalgo-1.0.9.dist-info/top_level.txt
backtrader_moexalgo-1.0.9.dist-info/RECORD
